LICENSE
MANIFEST.in
README.md
setup.py
simplemail/__init__.py
simplemail/handlers.py
simplemail.egg-info/PKG-INFO
simplemail.egg-info/SOURCES.txt
simplemail.egg-info/dependency_links.txt
simplemail.egg-info/top_level.txt