Metadata-Version: 1.0
Name: simplemail
Version: 1.0
Summary: An easy way to send emails in Python
Home-page: https://github.com/thesharp/simplemail
Author: Ilya Otyutskiy
Author-email: ilya.otyutskiy@icloud.com
License: MIT
Platform: UNKNOWN
